torchpropel
