Metadata-Version: 2.1
Name: torchpropel
Version: 0.0.3
Summary: Probabilistic Parameteric Regression Loss (PROPEL)
Home-page: http://github.com/masadcv/PROPEL
Author: Muhammad Asad
Author-email: muhammad.asad@kcl.ac.uk
License: BSD-3-Clause
Keywords: regression probabilistic neural networks machine learning
Platform: UNKNOWN
Classifier: Operating System :: OS Independent
Classifier: License :: OSI Approved :: BSD License
Classifier: Programming Language :: Python :: 3
